ytserver/functions/__init__.py
ytserver/functions/formats.py
ytserver/functions/info.py
ytserver/functions/instance.py
ytserver/functions/matching.py
ytserver/main.py
ytserver/models/__init__.py
ytserver/models/format.py
ytserver/models/formats.py
ytserver/models/video.py
ytserver-0.1.0.2.dist-info/LICENSE
ytserver-0.1.0.2.dist-info/METADATA
ytserver-0.1.0.2.dist-info/WHEEL
ytserver-0.1.0.2.dist-info/entry_points.txt
ytserver-0.1.0.2.dist-info/RECORD
