Metadata-Version: 2.1
Name: ytserver
Version: 0.1.0.2
Summary: A server for yt-dlp to download videos
Author: Mohammed Alsahli
Author-email: mohammed.saud.alsahli@gmail.com
Requires-Python: >=3.10,<4.0
Classifier: Programming Language :: Python :: 3
Classifier: Programming Language :: Python :: 3.10
Classifier: Programming Language :: Python :: 3.11
Classifier: Programming Language :: Python :: 3.12
Requires-Dist: fastapi[all] (>=0.109.0,<0.110.0)
Requires-Dist: pydantic (>=2.5.3,<3.0.0)
Requires-Dist: uvicorn[standard] (>=0.27.0,<0.28.0)
Requires-Dist: yt-dlp (>=2023.12.30,<2024.0.0)
